randomForestRules/__init__.py
randomForestRules/randomForestRules.py
randomForestRules_lukassykora-1.1.2.dist-info/LICENSE
randomForestRules_lukassykora-1.1.2.dist-info/METADATA
randomForestRules_lukassykora-1.1.2.dist-info/WHEEL
randomForestRules_lukassykora-1.1.2.dist-info/top_level.txt
randomForestRules_lukassykora-1.1.2.dist-info/RECORD
