Metadata-Version: 2.1
Name: randomForestRules-lukassykora
Version: 1.1.2
Summary: Random forest classification rules mining package
Home-page: https://github.com/lukassykora/randomForestRules
Author: Lukas Sykora
Author-email: lukassykora@seznam.cz
License: UNKNOWN
Platform: UNKNOWN
Classifier: Programming Language :: Python :: 3
Classifier: License :: OSI Approved :: MIT License
Classifier: Operating System :: OS Independent
Requires-Python: >=3.6
Requires-Dist: pandas
Requires-Dist: numpy
Requires-Dist: sklearn
Requires-Dist: typing
